mi/__init__.py
mi/cli.py
mi/test.py
mi/tf.py
mi/__pycache__/__init__.cpython-36.pyc
mi/__pycache__/test.cpython-36.pyc
mi/app/README.md
mi/app/__init__.py
mi/app/app1.py
mi/app/app2.py
mi/app/base_app.py
mi/app/dba_app.py
mi/app/email_apps.py
mi/app/helloworld.py
mi/app/hive_app.py
mi/app/iapp.py
mi/app/lac_app.py
mi/app/mongo.py
mi/app/mp3.py
mi/app/nlp_app.py
mi/app/nni_app.py
mi/app/ocr_app.py
mi/app/s.py
mi/app/search_data_transform.py
mi/app/simbert_app.py
mi/app/streamlit_.py
mi/app/streamlit_app.py
mi/app/zk_app.py
mi/app/__pycache__/__init__.cpython-36.pyc
mi/app/__pycache__/app1.cpython-36.pyc
mi/app/__pycache__/app2.cpython-36.pyc
mi/app/__pycache__/base_app.cpython-36.pyc
mi/app/__pycache__/helloworld.cpython-36.pyc
mi/app/__pycache__/hive_app.cpython-36.pyc
mi/app/__pycache__/iapp.cpython-36.pyc
mi/app/__pycache__/lac_app.cpython-36.pyc
mi/app/__pycache__/mongo.cpython-36.pyc
mi/app/__pycache__/mp3.cpython-36.pyc
mi/app/__pycache__/ocr_app.cpython-36.pyc
mi/app/__pycache__/simbert_app.cpython-36.pyc
mi/app/__pycache__/zk_app.cpython-36.pyc
mi/app/static/index.html
mi/bot/__init__.py
mi/cloudml/__init__.py
mi/cloudml/bash/__init__.py
mi/cloudml/bash/createDev.sh
mi/cloudml/bash/createDevCpu1.sh
mi/cloudml/bash/createDevCpu10.sh
mi/cloudml/bash/createDevCpu2.sh
mi/cloudml/bash/createDevCpu3.sh
mi/cloudml/bash/createDevCpu4.sh
mi/cloudml/bash/createDevCpu5.sh
mi/cloudml/bash/createDevCpu6.sh
mi/cloudml/bash/createDevCpu666.sh
mi/cloudml/bash/createDevCpu7.sh
mi/cloudml/bash/createDevCpu8.sh
mi/cloudml/bash/createDevCpu9.sh
mi/cloudml/bash/createDevGpu1.sh
mi/cloudml/bash/createDevGpu2.sh
mi/cloudml/bash/createDevGpuV100.sh
mi/cloudml/bash/createDevGpuV100_.sh
mi/cloudml/bash/createDevMaster.sh
mi/cloudml/bash/createDevMasterCpu.sh
mi/cloudml/bash/createDev_preferred.sh
mi/cloudml/bash/createImage.sh
mi/cloudml/bash/createTensorBoard.sh
mi/cloudml/bash/logs.sh
mi/cloudml/bash/quota.sh
mi/cloudml/bash/s.sh
mi/cloudml/bash/submit.sh
mi-2021.1.22.18.40.42.dist-info/METADATA
mi-2021.1.22.18.40.42.dist-info/WHEEL
mi-2021.1.22.18.40.42.dist-info/entry_points.txt
mi-2021.1.22.18.40.42.dist-info/top_level.txt
mi-2021.1.22.18.40.42.dist-info/RECORD
