Metadata-Version: 2.1
Name: mi
Version: 2021.1.22.18.40.42
Summary: description
Home-page: https://github.com/Jie-Yuan/mi
Author: JieYuan
Author-email: 313303303@qq.com
Maintainer: JieYuan
Maintainer-email: 313303303@qq.com
License: MIT
Keywords: tool wheel,yuanjie,utils
Platform: all
Classifier: Operating System :: OS Independent
Classifier: Intended Audience :: Developers
Classifier: License :: OSI Approved :: MIT License
Classifier: Programming Language :: Python :: 3.6
Classifier: Programming Language :: Python :: Implementation
Requires-Python: >=3.5
Requires-Dist: meutils
Requires-Dist: py2neo
Requires-Dist: pymysql
Requires-Dist: pymongo
Requires-Dist: pymilvus
Requires-Dist: redis-py-cluster
Requires-Dist: apollo-client
Requires-Dist: jovian
Requires-Dist: wandb
